spamdfba/.DS_Store
spamdfba/__init__.py
spamdfba/distribute.py
spamdfba/stats.py
spamdfba/toolkit.py
spamdfba/toymodels.py
spamdfba-1.1.0.dist-info/WHEEL
spamdfba-1.1.0.dist-info/METADATA
spamdfba-1.1.0.dist-info/RECORD
