Metadata-Version: 2.1
Name: spamdfba
Version: 1.1.0
Summary: 
Author: ParsaGhadermazi
Author-email: 54489047+ParsaGhadermazi@users.noreply.github.com
Requires-Python: >=3.10,<4.0
Classifier: Programming Language :: Python :: 3
Classifier: Programming Language :: Python :: 3.10
Requires-Dist: SciPy (>=1.11.4,<2.0.0)
Requires-Dist: cobra (>=0.27.0,<0.28.0)
Requires-Dist: ipywidgets (>=8.1.1,<9.0.0)
Requires-Dist: kaleido (==0.2.1)
Requires-Dist: nbformat (>=5.9.2,<6.0.0)
Requires-Dist: plotly (>=5.17.0,<6.0.0)
Requires-Dist: ray (>=2.7.1,<3.0.0)
Requires-Dist: torch (>=2.1.0,<3.0.0)
Project-URL: documentation, https://chan-csu.github.io/SPAM-DFBA/
